llm_wrapper/__init__.py
llm_wrapper/core.py
llm_wrapper/providers/__init__.py
llm_wrapper/providers/anthropic_provider.py
llm_wrapper/providers/base_provider.py
llm_wrapper/providers/google_provider.py
llm_wrapper/providers/ollama_provider.py
llm_wrapper/providers/openai_provider.py
llm_wrapper/providers/provider_enum.py
tests/__init__.py
tests/test_core.py
tests/test_providers.py
langchainbridge-1.0.1.dist-info/LICENSE
langchainbridge-1.0.1.dist-info/METADATA
langchainbridge-1.0.1.dist-info/WHEEL
langchainbridge-1.0.1.dist-info/top_level.txt
langchainbridge-1.0.1.dist-info/RECORD
