Metadata-Version: 2.1
Name: langchainbridge
Version: 1.0.1
Summary: A unified wrapper for various LLM providers using LangChain.
Home-page: https://github.com/maheshawasare/langchainbridge
Author: Mahesh Awasare
Author-email: maheshawasare@gmail.com
Classifier: Programming Language :: Python :: 3
Classifier: License :: OSI Approved :: MIT License
Classifier: Operating System :: OS Independent
Requires-Python: >=3.6
License-File: LICENSE
Requires-Dist: langchain-google-genai
Requires-Dist: langchain-openai
Requires-Dist: langchain-anthropic
Requires-Dist: requests
